undoc/__init__.py
undoc/_native.py
undoc/undoc.py
undoc/lib/linux-x64/libundoc.so
undoc/lib/osx-arm64/libundoc.dylib
undoc/lib/osx-x64/libundoc.dylib
undoc/lib/win-x64/undoc.dll
undoc-0.1.13.dist-info/METADATA
undoc-0.1.13.dist-info/WHEEL
undoc-0.1.13.dist-info/top_level.txt
undoc-0.1.13.dist-info/RECORD
