Metadata-Version: 2.4
Name: undoc
Version: 0.1.13
Summary: High-performance Microsoft Office document extraction to Markdown
Author-email: iyulab <tech@iyulab.com>
License: MIT
Project-URL: Homepage, https://github.com/iyulab/undoc
Project-URL: Documentation, https://github.com/iyulab/undoc#readme
Project-URL: Repository, https://github.com/iyulab/undoc
Project-URL: Issues, https://github.com/iyulab/undoc/issues
Keywords: office,docx,xlsx,pptx,markdown,extraction
Classifier: Development Status :: 4 - Beta
Classifier: Intended Audience :: Developers
Classifier: License :: OSI Approved :: MIT License
Classifier: Programming Language :: Python :: 3
Classifier: Programming Language :: Python :: 3.9
Classifier: Programming Language :: Python :: 3.10
Classifier: Programming Language :: Python :: 3.11
Classifier: Programming Language :: Python :: 3.12
Classifier: Operating System :: Microsoft :: Windows
Classifier: Operating System :: POSIX :: Linux
Classifier: Operating System :: MacOS :: MacOS X
Classifier: Topic :: Software Development :: Libraries :: Python Modules
Classifier: Topic :: Text Processing :: Markup
Requires-Python: >=3.9
Provides-Extra: dev
Requires-Dist: pytest>=7.0; extra == "dev"
Requires-Dist: pytest-cov>=4.0; extra == "dev"
Requires-Dist: black>=23.0; extra == "dev"
Requires-Dist: mypy>=1.0; extra == "dev"
